LuBan/__init__.py
LuBan/__init__.pyd
LuBan/__version.pyd
LuBan/_contrib/__init__.py
LuBan/_contrib/__init__.pyd
LuBan/_contrib/_constants.pyd
LuBan/_contrib/_constants.pyi
LuBan/core/__init__.py
LuBan/core/__init__.pyd
LuBan/core/_config_manager.pyd
LuBan/core/_config_manager.pyi
LuBan/core/_env_manager.pyd
LuBan/core/_env_manager.pyi
LuBan/core/_singleton_meta.pyd
LuBan/core/_singleton_meta.pyi
LuBan/core/common.pyd
LuBan/core/common.pyi
LuBan/core/typings.pyd
LuBan/core/typings.pyi
LuBan/exceptions/_AppServiceProcessInterrupt.pyd
LuBan/exceptions/_AppServiceProcessInterrupt.pyi
LuBan/exceptions/_InstantiationException.pyd
LuBan/exceptions/_InstantiationException.pyi
LuBan/exceptions/__init__.py
LuBan/exceptions/__init__.pyd
LuBan/framework/__init__.py
LuBan/framework/__init__.pyd
LuBan/framework/_app_service_container.pyd
LuBan/framework/_app_service_container.pyi
LuBan/framework/_app_service_interface.pyd
LuBan/framework/_app_service_interface.pyi
LuBan/framework/_app_service_manager.pyd
LuBan/framework/_app_service_manager.pyi
LuBan/framework/support/__init__.pyd
LuBan/framework/support/_config_support.pyd
LuBan/framework/support/_global_share_vars_support.pyd
LuBan/framework/support/_hook_support.pyd
LuBan/framework/support/_ipc_support.pyd
LuBan/framework/support/_process_service_support.pyd
LuBan/helper/__init__.py
LuBan/helper/__init__.pyd
LuBan/helper/_arr.pyd
LuBan/helper/_arr.pyi
LuBan/helper/_dt.pyd
LuBan/helper/_dt.pyi
LuBan/helper/_file.pyd
LuBan/helper/_file.pyi
LuBan/helper/_hash.pyd
LuBan/helper/_hash.pyi
LuBan/helper/_str.pyd
LuBan/helper/_str.pyi
LuBan/helper/_type.pyd
LuBan/helper/_type.pyi
LuBan/setuptools/__init__.pyd
LuBan/setuptools/_module_finder.pyd
LuBan/setuptools/build2_exe.pyd
LuBan/setuptools/build2_pkg.pyd
LuBan/setuptools/commands/__init__.pyd
LuBan/setuptools/commands/_build_ext.pyd
LuBan/utils/__init__.py
LuBan/utils/__init__.pyd
LuBan/utils/crypto/__init__.py
LuBan/utils/crypto/__init__.pyd
LuBan/utils/crypto/_aes.pyd
maxton-0.1.10.dist-info/LICENSE
maxton-0.1.10.dist-info/METADATA
maxton-0.1.10.dist-info/WHEEL
maxton-0.1.10.dist-info/top_level.txt
maxton-0.1.10.dist-info/RECORD
